azure/__init__.py
azure/datalake/__init__.py
azure/datalake/gen2/__init__.py
azure/datalake/gen2/client.py
tests/__init__.py
tests/test_filesystem.py
pydatalake_gen2-0.0.10.dist-info/LICENSE
pydatalake_gen2-0.0.10.dist-info/METADATA
pydatalake_gen2-0.0.10.dist-info/WHEEL
pydatalake_gen2-0.0.10.dist-info/top_level.txt
pydatalake_gen2-0.0.10.dist-info/RECORD
