Metadata-Version: 2.1
Name: pydatalake-gen2
Version: 0.0.10
Summary: REST API Client to Azure Data Lake Gen2
Home-page: https://github.com/estatic/pydatalake-gen2
Author: Ivan Grunev
Author-email: ivan.grunev@gmail.com
License: UNKNOWN
Platform: UNKNOWN
Classifier: Programming Language :: Python :: 3
Classifier: Operating System :: OS Independent
Classifier: Topic :: Software Development :: Libraries
Classifier: Topic :: Software Development :: Libraries :: Python Modules
Requires-Python: >=3.4
